backports_abc.py
setup.py
singledispatch.py
singledispatch_helpers.py
backports/__init__.py
backports/ssl_match_hostname/__init__.py
mavnbclient/DefaultHttpWrapper.py
mavnbclient/HttpClientWrapper.py
mavnbclient/HttpServerWrapper.py
mavnbclient/JsonDecoder.py
mavnbclient/MavNBClient.py
mavnbclient/Message.py
mavnbclient/NBException.py
mavnbclient/__init__.py
mavnbclient.egg-info/PKG-INFO
mavnbclient.egg-info/SOURCES.txt
mavnbclient.egg-info/dependency_links.txt
mavnbclient.egg-info/top_level.txt
mavnbclient.egg-info/zip-safe
tornado/__init__.py
tornado/_locale_data.py
tornado/auth.py
tornado/autoreload.py
tornado/concurrent.py
tornado/curl_httpclient.py
tornado/escape.py
tornado/gen.py
tornado/http1connection.py
tornado/httpclient.py
tornado/httpserver.py
tornado/httputil.py
tornado/ioloop.py
tornado/iostream.py
tornado/locale.py
tornado/locks.py
tornado/log.py
tornado/netutil.py
tornado/options.py
tornado/process.py
tornado/queues.py
tornado/routing.py
tornado/simple_httpclient.py
tornado/stack_context.py
tornado/tcpclient.py
tornado/tcpserver.py
tornado/template.py
tornado/testing.py
tornado/util.py
tornado/web.py
tornado/websocket.py
tornado/wsgi.py
tornado/platform/__init__.py
tornado/platform/asyncio.py
tornado/platform/auto.py
tornado/platform/caresresolver.py
tornado/platform/common.py
tornado/platform/epoll.py
tornado/platform/interface.py
tornado/platform/kqueue.py
tornado/platform/posix.py
tornado/platform/select.py
tornado/platform/twisted.py
tornado/platform/windows.py
tornado/test/__init__.py
tornado/test/__main__.py
tornado/test/asyncio_test.py
tornado/test/auth_test.py
tornado/test/autoreload_test.py
tornado/test/concurrent_test.py
tornado/test/curl_httpclient_test.py
tornado/test/escape_test.py
tornado/test/gen_test.py
tornado/test/http1connection_test.py
tornado/test/httpclient_test.py
tornado/test/httpserver_test.py
tornado/test/httputil_test.py
tornado/test/import_test.py
tornado/test/ioloop_test.py
tornado/test/iostream_test.py
tornado/test/locale_test.py
tornado/test/locks_test.py
tornado/test/log_test.py
tornado/test/netutil_test.py
tornado/test/options_test.py
tornado/test/process_test.py
