Metadata-Version: 1.0
Name: mavnbclient
Version: 0.6
Summary: NB API wrapper for Bot development
Home-page: https://github.com/Manoor00/MavNBClient
Author: Sunil Manoor
Author-email: sunil.manoor@mavenir.com
License: LGPL
Platform: UNKNOWN
